src/__init__.py
src/aspyco.py
aspyco-1.1.dist-info/entry_points.txt
aspyco-1.1.dist-info/LICENSE.md
aspyco-1.1.dist-info/WHEEL
aspyco-1.1.dist-info/METADATA
aspyco-1.1.dist-info/RECORD
