Metadata-Version: 2.1
Name: aspyco
Version: 1.1
Summary: Upload and start your custom payloads remotely !
Home-page: https://github.com/Processus-Thief/Aspyco
License: GPL-3.0-only
Keywords: aspyco,windows,psexec,smbexec,reverse,shell,credentials
Author: Processus Thief
Author-email: aspyco@thiefin.fr
Maintainer: Processus Thief
Maintainer-email: aspyco@thiefin.fr
Requires-Python: >=3.6,<4.0
Classifier: License :: OSI Approved :: GNU General Public License v3 (GPLv3)
Classifier: Programming Language :: Python :: 3
Classifier: Programming Language :: Python :: 3.6
Classifier: Programming Language :: Python :: 3.7
Classifier: Programming Language :: Python :: 3.8
Classifier: Programming Language :: Python :: 3.9
Classifier: Programming Language :: Python :: 3.10
Requires-Dist: impacket (>=0.10.0,<0.11.0)
Project-URL: Bug Tracker, https://github.com/Processus-Thief/Aspyco/issues
Project-URL: Documentation, https://github.com/Processus-Thief/Aspyco
Project-URL: Repository, https://github.com/Processus-Thief/Aspyco
